cryptg/__init__.py
telethon_tgcrypto-0.0.3.dist-info/LICENSE
telethon_tgcrypto-0.0.3.dist-info/METADATA
telethon_tgcrypto-0.0.3.dist-info/WHEEL
telethon_tgcrypto-0.0.3.dist-info/top_level.txt
telethon_tgcrypto-0.0.3.dist-info/RECORD
